spyden/__init__.py
spyden/_version.py
spyden/cpad.py
spyden/noisestats.py
spyden/snr.py
spyden/template.py
spyden_pulsar-0.1.1.dist-info/licenses/LICENSE
spyden_pulsar-0.1.1.dist-info/METADATA
spyden_pulsar-0.1.1.dist-info/WHEEL
spyden_pulsar-0.1.1.dist-info/top_level.txt
spyden_pulsar-0.1.1.dist-info/RECORD
