Metadata-Version: 2.4
Name: spyden-pulsar
Version: 0.1.1
Summary: Functions to evaluate the signal-to-noise ratio of radio transients
Author-email: Vincent Morello <vmorello@gmail.com>
License-Expression: MIT
Project-URL: Homepage, https://github.com/v-morello/spyden
Classifier: Programming Language :: Python :: 3
Classifier: Operating System :: Unix
Classifier: Topic :: Scientific/Engineering :: Astronomy
Requires-Python: >=3.9
License-File: LICENSE
Requires-Dist: numpy>=1.13
Requires-Dist: matplotlib>=2.0
Provides-Extra: dev
Requires-Dist: isort; extra == "dev"
Requires-Dist: flake8; extra == "dev"
Requires-Dist: black; extra == "dev"
Requires-Dist: pytest; extra == "dev"
Requires-Dist: pytest-cov; extra == "dev"
Requires-Dist: build; extra == "dev"
Requires-Dist: twine; extra == "dev"
Dynamic: license-file
